carlson_fractional_vegetation_cover/__init__.py
carlson_fractional_vegetation_cover/carlson_fractional_vegetation_cover.py
carlson_fractional_vegetation_cover-1.0.1.dist-info/licenses/LICENSE
carlson_fractional_vegetation_cover-1.0.1.dist-info/METADATA
carlson_fractional_vegetation_cover-1.0.1.dist-info/WHEEL
carlson_fractional_vegetation_cover-1.0.1.dist-info/top_level.txt
carlson_fractional_vegetation_cover-1.0.1.dist-info/RECORD
